Metadata-Version: 2.1
Name: mysqlorm
Version: 0.2
Summary: A simple ORM MySQL operation Library, running on Python3.
Home-page: https://github.com/cirlmcesc/mysqlorm
Author: cirlmcesc
Author-email: cirlmcesc_ma@163.com
License: UNKNOWN
Keywords: mysql orm
Platform: UNKNOWN
Classifier: Development Status :: 3 - Alpha
Classifier: Intended Audience :: Developers
Classifier: Topic :: Software Development :: Libraries :: Python Modules
Classifier: License :: OSI Approved :: MIT License
Classifier: Programming Language :: Python :: 2
Classifier: Programming Language :: Python :: 2.7
Classifier: Programming Language :: Python :: 3
Classifier: Programming Language :: Python :: 3.4
Classifier: Programming Language :: Python :: 3.5
Classifier: Programming Language :: Python :: 3.6
Classifier: Programming Language :: Python :: 3.7
Provides-Extra: dev
Provides-Extra: test
